_frm_cpp.cpython-39-i386-linux-gnu.so
frm/__init__.py
frm/_frm_py/preprocessing.py
frm/_frm_py/miner.py
frm/_frm_py/__init__.py
frm/_frm_py/patterns.py
frm/_frm_py/motif.py
frm_miner-0.0.8.dist-info/WHEEL
frm_miner-0.0.8.dist-info/LICENSE
frm_miner-0.0.8.dist-info/RECORD
frm_miner-0.0.8.dist-info/top_level.txt
frm_miner-0.0.8.dist-info/METADATA
